README.txt
setup.py
atreal/__init__.py
atreal.layouts.egg-info/PKG-INFO
atreal.layouts.egg-info/SOURCES.txt
atreal.layouts.egg-info/dependency_links.txt
atreal.layouts.egg-info/entry_points.txt
atreal.layouts.egg-info/namespace_packages.txt
atreal.layouts.egg-info/not-zip-safe
atreal.layouts.egg-info/requires.txt
atreal.layouts.egg-info/top_level.txt
atreal/layouts/__init__.py
atreal/layouts/configure.zcml
atreal/layouts/interfaces.py
atreal/layouts/skins.zcml
atreal/layouts/browser/__init__.py
atreal/layouts/browser/atreallayouts_icon.png
atreal/layouts/browser/configure.zcml
atreal/layouts/browser/controlpanel.py
atreal/layouts/browser/document_actions.pt
atreal/layouts/browser/listing.pt
atreal/layouts/browser/listing.py
atreal/layouts/browser/listing_macro.pt
atreal/layouts/browser/listing_table.pt
atreal/layouts/browser/viewlets.py
atreal/layouts/locales/atreal.layouts.pot
atreal/layouts/locales/fr/LC_MESSAGES/atreal.layouts.po
atreal/layouts/profiles/default/actionicons.xml
atreal/layouts/profiles/default/browserlayer.xml
atreal/layouts/profiles/default/controlpanel.xml
atreal/layouts/profiles/default/metadata.xml
atreal/layouts/profiles/document_actions_as_icons/browserlayer.xml
atreal/layouts/profiles/document_actions_as_icons/viewlets.xml
atreal/layouts/profiles/extedit/actions.xml
atreal/layouts/profiles/extedit/cssregistry.xml
atreal/layouts/profiles/extedit/skins.xml
atreal/layouts/profiles/icontheme_tatooine/skins.xml
atreal/layouts/profiles/restricted_access/browserlayer.xml
atreal/layouts/skins/atreal_layouts_extedit/extedit.css.dtml
atreal/layouts/skins/atreal_layouts_icontheme_tatooine/application.png
atreal/layouts/skins/atreal_layouts_icontheme_tatooine/audio.png
atreal/layouts/skins/atreal_layouts_icontheme_tatooine/avi.png
atreal/layouts/skins/atreal_layouts_icontheme_tatooine/c.png
atreal/layouts/skins/atreal_layouts_icontheme_tatooine/core.png
atreal/layouts/skins/atreal_layouts_icontheme_tatooine/cpp.png
atreal/layouts/skins/atreal_layouts_icontheme_tatooine/deb.png
atreal/layouts/skins/atreal_layouts_icontheme_tatooine/doc.png
atreal/layouts/skins/atreal_layouts_icontheme_tatooine/document_icon.gif
atreal/layouts/skins/atreal_layouts_icontheme_tatooine/down.png
atreal/layouts/skins/atreal_layouts_icontheme_tatooine/dvi.png
