Metadata-Version: 1.0
Name: atreal.layouts
Version: 0.6.2
Summary: Various layouts for Plone
Home-page: https://svn.plone.org/svn/collective/atreal.layouts
Author: atReal
Author-email: contact@atreal.net
License: GPL
Keywords: atreal plone layouts
Platform: UNKNOWN
Classifier: Framework :: Plone
Classifier: Programming Language :: Python
